rtl/LSU.v
module LSU (
    input       [2:0]   funct3M,
    input       [1:0]   ALUResultM,         //bottom 2 bits for alignment
    input       [31:0]  RD,                 //RD from DMEM, then to ReadDataW
    output reg  [3:0]   BW,                 //BW from funct3M, thento DMEM
    output reg  [31:0]  Formatted_ReadDataM 
);

always @(*) begin
    //Default
    BW = 4'b0000;
    Formatted_ReadDataM = 32'h00000000;

    //Write path -- generate byte enable (BW) for DMEM
    //bottom 2 bit of funct3M: 00(sb), 01(sh), 10(sw)
    /*NOTE: Load instruction share these code, 
    but DMEM will just ignore the BW output if WE pin is set to 0 */
    case (funct3M[1:0])
        2'b00: begin
            case (ALUResultM)       //sb, save byte
                2'b00: BW = 4'b0001;
                2'b01: BW = 4'b0010;
                2'b10: BW = 4'b0100;
                2'b11: BW = 4'b1000;
            endcase
        end
        2'b01: begin
            case (ALUResultM[1])    //sh, save halfword
                1'b0: BW = 4'b0011;
                1'b1: BW = 4'b1100;
            endcase
        end
        2'b10: begin
            BW = 4'b1111;           //sw, save word
        end
    endcase

    //Read path
    case (funct3M)
        3'b000: begin   //lb (load byte, sign-extended)
            case (ALUResultM)
                2'b00: Formatted_ReadDataM = {{24{RD[7]}}, RD[7:0]};
                2'b01: Formatted_ReadDataM = {{24{RD[15]}}, RD[15:8]};
                2'b10: Formatted_ReadDataM = {{24{RD[23]}}, RD[23:16]};
                2'b11: Formatted_ReadDataM = {{24{RD[23]}}, RD[23:16]};
            endcase
        end
        3'b100: begin   //lbu (load byte unsigned, zero-extended)
            case (ALUResultM)
                2'b00: Formatted_ReadDataM = {24'b0, RD[7:0]};
                2'b01: Formatted_ReadDataM = {24'b0, RD[15:8]};
                2'b10: Formatted_ReadDataM = {24'b0, RD[23:16]};
                2'b11: Formatted_ReadDataM = {24'b0, RD[23:16]};
            endcase
        end
        3'b001: begin   //lh (load halfword, sign-extended)
            case (ALUResultM[1])
                1'b0: Formatted_ReadDataM = {{16{RD[15]}}, RD[15:0]};
                1'b1: Formatted_ReadDataM = {{16{RD[31]}}, RD[31:16]};
            endcase
        end
        3'b101: begin   //lhu (Load Halfword Unsigned, Zero-Extended)
            case (ALUResultM[1])
                1'b0: Formatted_ReadDataM = {16'b0, RD[15:0]};
                1'b1: Formatted_ReadDataM = {16'b0, RD[31:16]};
            endcase
        end
        3'b010: begin   //lw (load word)
            Formatted_ReadDataM = RD;
        end
        default: begin
            Formatted_ReadDataM = RD;
        end
    endcase
end
endmodule

tb/tb_LSU.v
`timescale 1ns / 1ps

module tb_LSU_all();

    // Inputs to LSU
    reg  [2:0]  funct3M;
    reg  [1:0]  ALUResultM;
    reg  [31:0] RD;
    
    // Outputs from LSU
    wire [3:0]  BW;
    wire [31:0] Formatted_ReadDataM;

    // Instantiate the Unit Under Test (UUT)
    LSU uut (
        .funct3M(funct3M),
        .ALUResultM(ALUResultM),
        .RD(RD),
        .BW(BW),
        .Formatted_ReadDataM(Formatted_ReadDataM)
    );

    initial begin
        $dumpfile("build/lsu_all_waveform.vcd");
        $dumpvars(0, tb_LSU_all);

        $display("=== STARTING COMPREHENSIVE LSU TEST (ALL 8 INSTRUCTIONS) ===");

        // ==========================================
        // PART 1: STORE INSTRUCTIONS (3 Instructions)
        // ==========================================

        // 1. sb (Store Byte) - funct3: 3'b000
        funct3M = 3'b000; 
        ALUResultM = 2'b10; // Byte lane 2
        RD = 32'h0;
        #10;
        $display("1. sb  -> Expected BW: 0100 | Actual BW: %b", BW);

        // 2. sh (Store Halfword) - funct3: 3'b001
        funct3M = 3'b001; 
        ALUResultM = 2'b10; // Upper halfword
        #10;
        $display("2. sh  -> Expected BW: 1100 | Actual BW: %b", BW);

        // 3. sw (Store Word) - funct3: 3'b010
        funct3M = 3'b010; 
        ALUResultM = 2'b00; 
        #10;
        $display("3. sw  -> Expected BW: 1111 | Actual BW: %b", BW);


        // ==========================================
        // PART 2: LOAD INSTRUCTIONS (5 Instructions)
        // ==========================================

        // 4. lb (Load Byte Signed) - funct3: 3'b000
        // Testing with 0x8A (bit 7 is 1, so it should sign-extend with f's)
        funct3M = 3'b000; 
        ALUResultM = 2'b00; 
        RD = 32'h0000008A; 
        #10;
        $display("4. lb  (signed)   -> Expected: ffffff8a | Actual: %h", Formatted_ReadDataM);

        // 5. lbu (Load Byte Unsigned) - funct3: 3'b100
        // Testing with the same 0x8A, but should zero-extend instead
        funct3M = 3'b100; 
        ALUResultM = 2'b00; 
        RD = 32'h0000008A; 
        #10;
        $display("5. lbu (unsigned) -> Expected: 0000008a | Actual: %h", Formatted_ReadDataM);

        // 6. lh (Load Halfword Signed) - funct3: 3'b001
        // Testing with 0x8FFF (bit 15 is 1, sign-extending upper bits)
        funct3M = 3'b001; 
        ALUResultM = 2'b00; 
        RD = 32'h00008FFF; 
        #10;
        $display("6. lh  (signed)   -> Expected: ffff8fff | Actual: %h", Formatted_ReadDataM);

        // 7. lhu (Load Halfword Unsigned) - funct3: 3'b101
        // Testing with 0x8FFF, zero-extending upper bits
        funct3M = 3'b101; 
        ALUResultM = 2'b00; 
        RD = 32'h00008FFF; 
        #10;
        $display("7. lhu (unsigned) -> Expected: 00008fff | Actual: %h", Formatted_ReadDataM);

        // 8. lw (Load Word) - funct3: 3'b010
        funct3M = 3'b010; 
        ALUResultM = 2'b00; 
        RD = 32'hDEADBEEF; 
        #10;
        $display("8. lw  (word)     -> Expected: deadbeef | Actual: %h", Formatted_ReadDataM);

        $display("=== ALL 8 INSTRUCTION TESTS COMPLETED SUCCESSFULLY ===");
        $finish;
    end

endmodule

lsu_all_waveform.vcd
$date
	Fri Sep 25 19:00:37 2026
$end
$version
	Icarus Verilog
$end
$timescale
	1ps
$end
$scope module tb_LSU_all $end
$var wire 32 ! Formatted_ReadDataM [31:0] $end
$var wire 4 " BW [3:0] $end
$var reg 2 # ALUResultM [1:0] $end
$var reg 32 $ RD [31:0] $end
$var reg 3 % funct3M [2:0] $end
$scope module uut $end
$var wire 2 & ALUResultM [1:0] $end
$var wire 32 ' RD [31:0] $end
$var wire 3 ( funct3M [2:0] $end
$var reg 4 ) BW [3:0] $end
$var reg 32 * Formatted_ReadDataM [31:0] $end
$upscope $end
$upscope $end
$enddefinitions $end
$comment Show the parameter values. $end
$dumpall
$end
#0
$dumpvars
b0 *
b100 )
b0 (
b0 '
b10 &
b0 %
b0 $
b10 #
b100 "
b0 !
$end
#10000
b1100 "
b1100 )
b1 %
b1 (
#20000
b1111 "
b1111 )
b0 #
b0 &
b10 %
b10 (
#30000
b11111111111111111111111110001010 !
b11111111111111111111111110001010 *
b1 "
b1 )
b10001010 $
b10001010 '
b0 %
b0 (
#40000
b10001010 !
b10001010 *
b1 "
b1 )
b100 %
b100 (
#50000
b11111111111111111000111111111111 !
b11111111111111111000111111111111 *
b11 "
b11 )
b1000111111111111 $
b1000111111111111 '
b1 %
b1 (
#60000
b1000111111111111 !
b1000111111111111 *
b11 "
b11 )
b101 %
b101 (
#70000
b11011110101011011011111011101111 !
b11011110101011011011111011101111 *
b1111 "
b1111 )
b11011110101011011011111011101111 $
b11011110101011011011111011101111 '
b10 %
b10 (
