rtl/ALU.v
module ALU (
    input wire [31:0]   SrcAE,
    input wire [31:0]   SrcBE,
    input wire [3:0]    ALUControlE,
    output reg [31:0]   ALUResultE,
    output              o_Zero //to Control_Unit, then to AND gate
);
    localparam c_ALU_OP_PASS = 4'h0;
    localparam c_ALU_OP_ADD  = 4'h1;
    localparam c_ALU_OP_SUB  = 4'h2;
    localparam c_ALU_OP_AND  = 4'h3;
    localparam c_ALU_OP_OR   = 4'h4;
    localparam c_ALU_OP_XOR  = 4'h5;
    localparam c_ALU_OP_SLL  = 4'h6;
    localparam c_ALU_OP_SRL  = 4'h7;
    localparam c_ALU_OP_SRA  = 4'h8;
    localparam c_ALU_OP_SLT  = 4'h9;
    localparam c_ALU_OP_SLTU = 4'hA;
    localparam c_ALU_OP_BNE  = 4'hB;
    localparam c_ALU_OP_BLT  = 4'hC;
    localparam c_ALU_OP_BGE  = 4'hD;
    localparam c_ALU_OP_BLTU = 4'hE;
    localparam c_ALU_OP_BGEU = 4'hF;
 
    // o_Zero becomes a "Branch Condition Met" flag for branch operations
    assign o_Zero = (ALUControlE == c_ALU_OP_BNE)  ? (SrcAE != SrcBE) :
                    (ALUControlE == c_ALU_OP_BLT)  ? ($signed(SrcAE) < $signed(SrcBE)) :
                    (ALUControlE == c_ALU_OP_BGE)  ? ($signed(SrcAE) >= $signed(SrcBE)) :
                    (ALUControlE == c_ALU_OP_BLTU) ? (SrcAE < SrcBE) :
                    (ALUControlE == c_ALU_OP_BGEU) ? (SrcAE >= SrcBE) :
                    (ALUResultE == 32'b0); // Default for ADD, SUB, BEQ, and logical ops
  
    always @ (*) begin
        case (ALUControlE)
            c_ALU_OP_PASS: ALUResultE = SrcBE;
            c_ALU_OP_ADD:  ALUResultE = SrcAE + SrcBE;
            c_ALU_OP_SUB:  ALUResultE = SrcAE - SrcBE;
            c_ALU_OP_AND:  ALUResultE = SrcAE & SrcBE;
            c_ALU_OP_OR:   ALUResultE = SrcAE | SrcBE;
            c_ALU_OP_XOR:  ALUResultE = SrcAE ^ SrcBE;
            c_ALU_OP_SLL:  ALUResultE = SrcAE << SrcBE[4:0];
            c_ALU_OP_SRL:  ALUResultE = SrcAE >> SrcBE[4:0];
            c_ALU_OP_SRA:  ALUResultE = $signed(SrcAE) >>> SrcBE[4:0];
            c_ALU_OP_SLT:   ALUResultE = ($signed(SrcAE) < $signed(SrcBE)) ? 32'd1 : 32'd0;
            c_ALU_OP_SLTU:  ALUResultE = ($unsigned(SrcAE) < $unsigned(SrcBE)) ? 32'd1 : 32'd0;
            default:       ALUResultE = 32'b0;
        endcase
    end
endmodule

tb/tb_ALU.v
`timescale 1ns / 1ps

module tb_ALU();

    // 1. Declare testbench signals
    reg  [31:0] SrcAE;
    reg  [31:0] SrcBE;
    reg  [3:0]  ALUControlE;
    
    wire [31:0] ALUResultE;
    wire        o_Zero;

    // 2. Instantiate the ALU
    ALU uut (
        .SrcAE(SrcAE),
        .SrcBE(SrcBE),
        .ALUControlE(ALUControlE),
        .ALUResultE(ALUResultE),
        .o_Zero(o_Zero)
    );

    // 3. Define localparams matching the ALU module for readability
    localparam c_ALU_OP_PASS = 4'h0;
    localparam c_ALU_OP_ADD  = 4'h1;
    localparam c_ALU_OP_SUB  = 4'h2;
    localparam c_ALU_OP_AND  = 4'h3;
    localparam c_ALU_OP_OR   = 4'h4;
    localparam c_ALU_OP_XOR  = 4'h5;
    localparam c_ALU_OP_SLL  = 4'h6;
    localparam c_ALU_OP_SRL  = 4'h7;
    localparam c_ALU_OP_SRA  = 4'h8;
    localparam c_ALU_OP_SLT  = 4'h9;
    localparam c_ALU_OP_SLTU = 4'hA;
    localparam c_ALU_OP_BNE  = 4'hB;
    localparam c_ALU_OP_BLT  = 4'hC;
    localparam c_ALU_OP_BGE  = 4'hD;
    localparam c_ALU_OP_BLTU = 4'hE;
    localparam c_ALU_OP_BGEU = 4'hF;

    // 4. Test Sequence
    initial begin
        $dumpfile("build/alu_waveform.vcd");
        $dumpvars(0, tb_ALU);

        $display("=== STARTING ALU COMPREHENSIVE TEST ===");

        // Test 0: PASS (Result = B)
        ALUControlE = c_ALU_OP_PASS; SrcAE = 32'hFFFFFFFF; SrcBE = 32'hA5A5A5A5; #10;
        $display("0. PASS -> Expected: a5a5a5a5, Z: 0 | Actual: %h, Z: %b", ALUResultE, o_Zero);

        // Test 1: ADD
        ALUControlE = c_ALU_OP_ADD;  SrcAE = 32'd20; SrcBE = 32'd10; #10;
        $display("1. ADD  -> Expected: 0000001e, Z: 0 | Actual: %h, Z: %b", ALUResultE, o_Zero);

        // Test 2: SUB 
        ALUControlE = c_ALU_OP_SUB;  SrcAE = 32'd20; SrcBE = 32'd20; #10;
        $display("2. SUB  -> Expected: 00000000, Z: 1 | Actual: %h, Z: %b", ALUResultE, o_Zero);

        // Test 3: AND
        ALUControlE = c_ALU_OP_AND;  SrcAE = 32'hF0F0F0F0; SrcBE = 32'h0F0F0F0F; #10;
        $display("3. AND  -> Expected: 00000000, Z: 1 | Actual: %h, Z: %b", ALUResultE, o_Zero);

        // Test 4: OR
        ALUControlE = c_ALU_OP_OR;   SrcAE = 32'hF0F0F0F0; SrcBE = 32'h0F0F0F0F; #10;
        $display("4. OR   -> Expected: ffffffff, Z: 0 | Actual: %h, Z: %b", ALUResultE, o_Zero);

        // Test 5: XOR
        ALUControlE = c_ALU_OP_XOR;  SrcAE = 32'hFFFFFFFF; SrcBE = 32'hA5A5A5A5; #10;
        $display("5. XOR  -> Expected: 5a5a5a5a, Z: 0 | Actual: %h, Z: %b", ALUResultE, o_Zero);

        // Test 6: SLL 
        ALUControlE = c_ALU_OP_SLL;  SrcAE = 32'h00000001; SrcBE = 32'd4; #10;
        $display("6. SLL  -> Expected: 00000010, Z: 0 | Actual: %h, Z: %b", ALUResultE, o_Zero);

        // Test 7: SRL 
        ALUControlE = c_ALU_OP_SRL;  SrcAE = 32'h80000000; SrcBE = 32'd4; #10;
        $display("7. SRL  -> Expected: 08000000, Z: 0 | Actual: %h, Z: %b", ALUResultE, o_Zero);

        // Test 8: SRA 
        ALUControlE = c_ALU_OP_SRA;  SrcAE = 32'h80000000; SrcBE = 32'd4; #10;
        $display("8. SRA  -> Expected: f8000000, Z: 0 | Actual: %h, Z: %b", ALUResultE, o_Zero);

        // Test 9: SLT 
        ALUControlE = c_ALU_OP_SLT;  SrcAE = 32'hFFFFFFFF; SrcBE = 32'h00000001; #10; // -1 < 1
        $display("9. SLT  -> Expected: 00000001, Z: 0 | Actual: %h, Z: %b", ALUResultE, o_Zero);

        // Test A: SLTU 
        ALUControlE = c_ALU_OP_SLTU; SrcAE = 32'hFFFFFFFF; SrcBE = 32'h00000001; #10; // 4,294,967,295 NOT < 1
        $display("A. SLTU -> Expected: 00000000, Z: 1 | Actual: %h, Z: %b", ALUResultE, o_Zero);

        // ---------------------------------------------------------
        // NEW TESTS: Branch Instructions (Checking Condition Flag)
        // ---------------------------------------------------------

        // Test B: BNE (Branch Not Equal)
        // A (10) != B (20) is TRUE. Expected: o_Zero = 1. ALUResult defaults to 0.
        ALUControlE = c_ALU_OP_BNE;  SrcAE = 32'd10; SrcBE = 32'd20; #10;
        $display("B. BNE  -> Expected: 00000000, Z: 1 | Actual: %h, Z: %b", ALUResultE, o_Zero);

        // Test C: BLT (Branch Less Than - Signed)
        // A (-1) < B (1) is TRUE. Expected: o_Zero = 1. ALUResult defaults to 0.
        ALUControlE = c_ALU_OP_BLT;  SrcAE = 32'hFFFFFFFF; SrcBE = 32'h00000001; #10;
        $display("C. BLT  -> Expected: 00000000, Z: 1 | Actual: %h, Z: %b", ALUResultE, o_Zero);

        // Test D: BGE (Branch Greater Than or Equal - Signed)
        // A (20) >= B (10) is TRUE. Expected: o_Zero = 1. ALUResult defaults to 0.
        ALUControlE = c_ALU_OP_BGE;  SrcAE = 32'd20; SrcBE = 32'd10; #10;
        $display("D. BGE  -> Expected: 00000000, Z: 1 | Actual: %h, Z: %b", ALUResultE, o_Zero);

        // Test E: BLTU (Branch Less Than - Unsigned)
        // A (5) < B (10) is TRUE. Expected: o_Zero = 1. ALUResult defaults to 0.
        ALUControlE = c_ALU_OP_BLTU; SrcAE = 32'd5; SrcBE = 32'd10; #10;
        $display("E. BLTU -> Expected: 00000000, Z: 1 | Actual: %h, Z: %b", ALUResultE, o_Zero);

        // Test F: BGEU (Branch Greater Than or Equal - Unsigned)
        // A (4,294,967,295) >= B (10) is TRUE. Expected: o_Zero = 1. ALUResult defaults to 0.
        ALUControlE = c_ALU_OP_BGEU; SrcAE = 32'hFFFFFFFF; SrcBE = 32'd10; #10;
        $display("F. BGEU -> Expected: 00000000, Z: 1 | Actual: %h, Z: %b", ALUResultE, o_Zero);

        // Test G: False condition check (Prove Z goes to 0 when false)
        // A (10) != B (10) is FALSE. Expected: o_Zero = 0.
        ALUControlE = c_ALU_OP_BNE;  SrcAE = 32'd10; SrcBE = 32'd10; #10;
        $display("G. BNEF -> Expected: 00000000, Z: 0 | Actual: %h, Z: %b", ALUResultE, o_Zero);

        $display("=== ALU TESTS COMPLETED ===");
        $finish;
    end

endmodule

build/alu_waveform.vcd
$date
	Sun Sep 27 22:38:10 2026
$end
$version
	Icarus Verilog
$end
$timescale
	1ps
$end
$scope module tb_ALU $end
$var wire 1 ! o_Zero $end
$var wire 32 " ALUResultE [31:0] $end
$var parameter 4 # c_ALU_OP_ADD $end
$var parameter 4 $ c_ALU_OP_AND $end
$var parameter 4 % c_ALU_OP_BGE $end
$var parameter 4 & c_ALU_OP_BGEU $end
$var parameter 4 ' c_ALU_OP_BLT $end
$var parameter 4 ( c_ALU_OP_BLTU $end
$var parameter 4 ) c_ALU_OP_BNE $end
$var parameter 4 * c_ALU_OP_OR $end
$var parameter 4 + c_ALU_OP_PASS $end
$var parameter 4 , c_ALU_OP_SLL $end
$var parameter 4 - c_ALU_OP_SLT $end
$var parameter 4 . c_ALU_OP_SLTU $end
$var parameter 4 / c_ALU_OP_SRA $end
$var parameter 4 0 c_ALU_OP_SRL $end
$var parameter 4 1 c_ALU_OP_SUB $end
$var parameter 4 2 c_ALU_OP_XOR $end
$var reg 4 3 ALUControlE [3:0] $end
$var reg 32 4 SrcAE [31:0] $end
$var reg 32 5 SrcBE [31:0] $end
$scope module uut $end
$var wire 4 6 ALUControlE [3:0] $end
$var wire 32 7 SrcAE [31:0] $end
$var wire 32 8 SrcBE [31:0] $end
$var wire 1 ! o_Zero $end
$var parameter 4 9 c_ALU_OP_ADD $end
$var parameter 4 : c_ALU_OP_AND $end
$var parameter 4 ; c_ALU_OP_BGE $end
$var parameter 4 < c_ALU_OP_BGEU $end
$var parameter 4 = c_ALU_OP_BLT $end
$var parameter 4 > c_ALU_OP_BLTU $end
$var parameter 4 ? c_ALU_OP_BNE $end
$var parameter 4 @ c_ALU_OP_OR $end
$var parameter 4 A c_ALU_OP_PASS $end
$var parameter 4 B c_ALU_OP_SLL $end
$var parameter 4 C c_ALU_OP_SLT $end
$var parameter 4 D c_ALU_OP_SLTU $end
$var parameter 4 E c_ALU_OP_SRA $end
$var parameter 4 F c_ALU_OP_SRL $end
$var parameter 4 G c_ALU_OP_SUB $end
$var parameter 4 H c_ALU_OP_XOR $end
$var reg 32 I ALUResultE [31:0] $end
$upscope $end
$upscope $end
$enddefinitions $end
$comment Show the parameter values. $end
$dumpall
b101 H
b10 G
b111 F
b1000 E
b1010 D
b1001 C
b110 B
b0 A
b100 @
b1011 ?
b1110 >
b1100 =
b1111 <
b1101 ;
b11 :
b1 9
b101 2
b10 1
b111 0
b1000 /
b1010 .
b1001 -
b110 ,
b0 +
b100 *
b1011 )
b1110 (
b1100 '
b1111 &
b1101 %
b11 $
b1 #
$end
#0
$dumpvars
b10100101101001011010010110100101 I
b10100101101001011010010110100101 8
b11111111111111111111111111111111 7
b0 6
b10100101101001011010010110100101 5
b11111111111111111111111111111111 4
b0 3
b10100101101001011010010110100101 "
0!
$end
#10000
b11110 "
b11110 I
b1010 5
b1010 8
b10100 4
b10100 7
b1 3
b1 6
#20000
1!
b0 "
b0 I
b10100 5
b10100 8
b10 3
b10 6
#30000
b1111000011110000111100001111 5
b1111000011110000111100001111 8
b11110000111100001111000011110000 4
b11110000111100001111000011110000 7
b11 3
b11 6
#40000
0!
b11111111111111111111111111111111 "
b11111111111111111111111111111111 I
b100 3
b100 6
#50000
b1011010010110100101101001011010 "
b1011010010110100101101001011010 I
b10100101101001011010010110100101 5
b10100101101001011010010110100101 8
b11111111111111111111111111111111 4
b11111111111111111111111111111111 7
b101 3
b101 6
#60000
b10000 "
b10000 I
b100 5
b100 8
b1 4
b1 7
b110 3
b110 6
#70000
b1000000000000000000000000000 "
b1000000000000000000000000000 I
b10000000000000000000000000000000 4
b10000000000000000000000000000000 7
b111 3
b111 6
#80000
b11111000000000000000000000000000 "
b11111000000000000000000000000000 I
b1000 3
b1000 6
#90000
b1 "
b1 I
b1 5
b1 8
b11111111111111111111111111111111 4
b11111111111111111111111111111111 7
b1001 3
b1001 6
#100000
1!
b0 "
b0 I
b1010 3
b1010 6
#110000
b10100 5
b10100 8
b1010 4
b1010 7
b1011 3
b1011 6
#120000
b1 5
b1 8
b11111111111111111111111111111111 4
b11111111111111111111111111111111 7
b1100 3
b1100 6
#130000
b1010 5
b1010 8
b10100 4
b10100 7
b1101 3
b1101 6
#140000
b101 4
b101 7
b1110 3
b1110 6
#150000
b11111111111111111111111111111111 4
b11111111111111111111111111111111 7
b1111 3
b1111 6
#160000
0!
b1010 4
b1010 7
b1011 3
b1011 6
