rtl/ALU.v
module ALU (
    input wire [31:0]   SrcAE,
    input wire [31:0]   SrcBE,
    input wire [3:0]    ALUControlE,
    output reg [31:0]   ALUResultE,
    output              o_Zero //to Control_Unit, then to AND gate
);
    localparam c_ALU_OP_PASS = 4'h0;
    localparam c_ALU_OP_ADD  = 4'h1;
    localparam c_ALU_OP_SUB  = 4'h2;
    localparam c_ALU_OP_AND  = 4'h3;
    localparam c_ALU_OP_OR   = 4'h4;
    localparam c_ALU_OP_XOR  = 4'h5;
    localparam c_ALU_OP_SLL  = 4'h6;
    localparam c_ALU_OP_SRL  = 4'h7;
    localparam c_ALU_OP_SRA  = 4'h8;
    localparam c_ALU_OP_SLT  = 4'h9;
    localparam c_ALU_OP_SLTU = 4'hA;
    localparam c_ALU_OP_BNE  = 4'hB;
    localparam c_ALU_OP_BLT  = 4'hC;
    localparam c_ALU_OP_BGE  = 4'hD;
    localparam c_ALU_OP_BLTU = 4'hE;
    localparam c_ALU_OP_BGEU = 4'hF;
 
    // o_Zero becomes a "Branch Condition Met" flag for branch operations
    assign o_Zero = (ALUControlE == c_ALU_OP_BNE)  ? (SrcAE != SrcBE) :
                    (ALUControlE == c_ALU_OP_BLT)  ? ($signed(SrcAE) < $signed(SrcBE)) :
                    (ALUControlE == c_ALU_OP_BGE)  ? ($signed(SrcAE) >= $signed(SrcBE)) :
                    (ALUControlE == c_ALU_OP_BLTU) ? (SrcAE < SrcBE) :
                    (ALUControlE == c_ALU_OP_BGEU) ? (SrcAE >= SrcBE) :
                    (ALUResultE == 32'b0); // Default for ADD, SUB, BEQ, and logical ops
  
    always @ (*) begin
        case (ALUControlE)
            c_ALU_OP_PASS: ALUResultE = SrcBE;
            c_ALU_OP_ADD:  ALUResultE = SrcAE + SrcBE;
            c_ALU_OP_SUB:  ALUResultE = SrcAE - SrcBE;
            c_ALU_OP_AND:  ALUResultE = SrcAE & SrcBE;
            c_ALU_OP_OR:   ALUResultE = SrcAE | SrcBE;
            c_ALU_OP_XOR:  ALUResultE = SrcAE ^ SrcBE;
            c_ALU_OP_SLL:  ALUResultE = SrcAE << SrcBE[4:0];
            c_ALU_OP_SRL:  ALUResultE = SrcAE >> SrcBE[4:0];
            c_ALU_OP_SRA:  ALUResultE = $signed(SrcAE) >>> SrcBE[4:0];
            c_ALU_OP_SLT:   ALUResultE = ($signed(SrcAE) < $signed(SrcBE)) ? 32'd1 : 32'd0;
            c_ALU_OP_SLTU:  ALUResultE = ($unsigned(SrcAE) < $unsigned(SrcBE)) ? 32'd1 : 32'd0;
            default:       ALUResultE = 32'b0;
        endcase
    end
endmodule

tb/tb_ALU.v
`timescale 1ns / 1ps

module tb_ALU();

    // 1. Declare testbench signals
    reg  [31:0] SrcAE;
    reg  [31:0] SrcBE;
    reg  [3:0]  ALUControlE;
    
    wire [31:0] ALUResultE;
    wire        o_Zero;

    // Error tracking counter
    integer error_count = 0;

    // 2. Instantiate the ALU
    ALU uut (
        .SrcAE(SrcAE),
        .SrcBE(SrcBE),
        .ALUControlE(ALUControlE),
        .ALUResultE(ALUResultE),
        .o_Zero(o_Zero)
    );

    // 3. Define localparams matching the ALU module for readability
    localparam c_ALU_OP_PASS = 4'h0;
    localparam c_ALU_OP_ADD  = 4'h1;
    localparam c_ALU_OP_SUB  = 4'h2;
    localparam c_ALU_OP_AND  = 4'h3;
    localparam c_ALU_OP_OR   = 4'h4;
    localparam c_ALU_OP_XOR  = 4'h5;
    localparam c_ALU_OP_SLL  = 4'h6;
    localparam c_ALU_OP_SRL  = 4'h7;
    localparam c_ALU_OP_SRA  = 4'h8;
    localparam c_ALU_OP_SLT  = 4'h9;
    localparam c_ALU_OP_SLTU = 4'hA;
    localparam c_ALU_OP_BNE  = 4'hB;
    localparam c_ALU_OP_BLT  = 4'hC;
    localparam c_ALU_OP_BGE  = 4'hD;
    localparam c_ALU_OP_BLTU = 4'hE;
    localparam c_ALU_OP_BGEU = 4'hF;

    // 4. Automated Testing Task with Expected Values on the Next Row
    task test_alu;
        input [79:0] test_name;
        input [3:0]  in_ctrl;
        input [31:0] in_a;
        input [31:0] in_b;
        input [31:0] exp_result;
        input        exp_zero;
        begin
            ALUControlE = in_ctrl;
            SrcAE       = in_a;
            SrcBE       = in_b;
            #10; // Wait for combinational logic to settle

            // Compare actual vs expected outputs
            if (ALUResultE === exp_result && o_Zero === exp_zero) begin
                $display("%-8s | [PASS]", test_name);
            end else begin
                $display("%-8s | [FAIL] ❌ MISMATCH DETECTED!", test_name);
                error_count = error_count + 1;
            end

            // Display Actual on this row, Expected on the next row below
            $display("    Actual   : Result=%h, Zero=%b", ALUResultE, o_Zero);
            $display("    Expected : Result=%h, Zero=%b", exp_result, exp_zero);
            $display("--------------------------------------------------------------------------------------------------------");
        end
    endtask

    // 5. Test Sequence
    initial begin
        $dumpfile("build/alu_waveform.vcd");
        $dumpvars(0, tb_ALU);

        $display("========================================================================================================");
        $display("                                   AUTOMATED ALU VERIFICATION SUITE                                     ");
        $display("========================================================================================================");

        // format: test_alu("NAME", ALUControlE, SrcAE, SrcBE, expected_result, expected_zero)

        // Arithmetic & Logic Operations
        test_alu("PASS", c_ALU_OP_PASS, 32'hFFFFFFFF, 32'hA5A5A5A5, 32'hA5A5A5A5, 1'b0);
        test_alu("ADD",  c_ALU_OP_ADD,  32'd20,       32'd10,       32'h0000001E, 1'b0);
        test_alu("SUB",  c_ALU_OP_SUB,  32'd20,       32'd20,       32'h00000000, 1'b1);
        test_alu("AND",  c_ALU_OP_AND,  32'hF0F0F0F0, 32'h0F0F0F0F, 32'h00000000, 1'b1);
        test_alu("OR",   c_ALU_OP_OR,   32'hF0F0F0F0, 32'h0F0F0F0F, 32'hFFFFFFFF, 1'b0);
        test_alu("XOR",  c_ALU_OP_XOR,  32'hFFFFFFFF, 32'hA5A5A5A5, 32'h5A5A5A5A, 1'b0);
        test_alu("SLL",  c_ALU_OP_SLL,  32'h00000001, 32'd4,        32'h00000010, 1'b0);
        test_alu("SRL",  c_ALU_OP_SRL,  32'h80000000, 32'd4,        32'h08000000, 1'b0);
        test_alu("SRA",  c_ALU_OP_SRA,  32'h80000000, 32'd4,        32'hF8000000, 1'b0);
        test_alu("SLT",  c_ALU_OP_SLT,  32'hFFFFFFFF, 32'h00000001, 32'h00000001, 1'b0);
        test_alu("SLTU", c_ALU_OP_SLTU, 32'hFFFFFFFF, 32'h00000001, 32'h00000000, 1'b1);

        // Branch Condition Checks
        test_alu("BNE",  c_ALU_OP_BNE,  32'd10,       32'd20,       32'h00000000, 1'b1);
        test_alu("BLT",  c_ALU_OP_BLT,  32'hFFFFFFFF, 32'h00000001, 32'h00000000, 1'b1);
        test_alu("BGE",  c_ALU_OP_BGE,  32'd20,       32'd10,       32'h00000000, 1'b1);
        test_alu("BLTU", c_ALU_OP_BLTU, 32'd5,        32'd10,       32'h00000000, 1'b1);
        test_alu("BGEU", c_ALU_OP_BGEU, 32'hFFFFFFFF, 32'd10,       32'h00000000, 1'b1);
        test_alu("BNEF", c_ALU_OP_BNE,  32'd10,       32'd10,       32'h00000000, 1'b0); // False condition check

        // Final Summary Report
        $display("========================================================================================================");
        if (error_count == 0) begin
            $display(" 🎉 ALL ALU TESTS PASSED! ALU logic is fully verified.");
        end else begin
            $display(" ❌ SIMULATION FAILED: Total Mismatches Found = %0d", error_count);
        end
        $display("========================================================================================================");
        $finish;
    end

endmodule

build/alu_waveform.vcd
$date
	Mon Oct  5 09:30:07 2026
$end
$version
	Icarus Verilog
$end
$timescale
	1ps
$end
$scope module tb_ALU $end
$var wire 1 ! o_Zero $end
$var wire 32 " ALUResultE [31:0] $end
$var parameter 4 # c_ALU_OP_ADD $end
$var parameter 4 $ c_ALU_OP_AND $end
$var parameter 4 % c_ALU_OP_BGE $end
$var parameter 4 & c_ALU_OP_BGEU $end
$var parameter 4 ' c_ALU_OP_BLT $end
$var parameter 4 ( c_ALU_OP_BLTU $end
$var parameter 4 ) c_ALU_OP_BNE $end
$var parameter 4 * c_ALU_OP_OR $end
$var parameter 4 + c_ALU_OP_PASS $end
$var parameter 4 , c_ALU_OP_SLL $end
$var parameter 4 - c_ALU_OP_SLT $end
$var parameter 4 . c_ALU_OP_SLTU $end
$var parameter 4 / c_ALU_OP_SRA $end
$var parameter 4 0 c_ALU_OP_SRL $end
$var parameter 4 1 c_ALU_OP_SUB $end
$var parameter 4 2 c_ALU_OP_XOR $end
$var reg 4 3 ALUControlE [3:0] $end
$var reg 32 4 SrcAE [31:0] $end
$var reg 32 5 SrcBE [31:0] $end
$var integer 32 6 error_count [31:0] $end
$scope module uut $end
$var wire 4 7 ALUControlE [3:0] $end
$var wire 32 8 SrcAE [31:0] $end
$var wire 32 9 SrcBE [31:0] $end
$var wire 1 ! o_Zero $end
$var parameter 4 : c_ALU_OP_ADD $end
$var parameter 4 ; c_ALU_OP_AND $end
$var parameter 4 < c_ALU_OP_BGE $end
$var parameter 4 = c_ALU_OP_BGEU $end
$var parameter 4 > c_ALU_OP_BLT $end
$var parameter 4 ? c_ALU_OP_BLTU $end
$var parameter 4 @ c_ALU_OP_BNE $end
$var parameter 4 A c_ALU_OP_OR $end
$var parameter 4 B c_ALU_OP_PASS $end
$var parameter 4 C c_ALU_OP_SLL $end
$var parameter 4 D c_ALU_OP_SLT $end
$var parameter 4 E c_ALU_OP_SLTU $end
$var parameter 4 F c_ALU_OP_SRA $end
$var parameter 4 G c_ALU_OP_SRL $end
$var parameter 4 H c_ALU_OP_SUB $end
$var parameter 4 I c_ALU_OP_XOR $end
$var reg 32 J ALUResultE [31:0] $end
$upscope $end
$scope task test_alu $end
$var reg 32 K exp_result [31:0] $end
$var reg 1 L exp_zero $end
$var reg 32 M in_a [31:0] $end
$var reg 32 N in_b [31:0] $end
$var reg 4 O in_ctrl [3:0] $end
$var reg 80 P test_name [79:0] $end
$upscope $end
$upscope $end
$enddefinitions $end
$comment Show the parameter values. $end
$dumpall
b101 I
b10 H
b111 G
b1000 F
b1010 E
b1001 D
b110 C
b0 B
b100 A
b1011 @
b1110 ?
b1100 >
b1111 =
b1101 <
b11 ;
b1 :
b101 2
b10 1
b111 0
b1000 /
b1010 .
b1001 -
b110 ,
b0 +
b100 *
b1011 )
b1110 (
b1100 '
b1111 &
b1101 %
b11 $
b1 #
$end
#0
$dumpvars
b1010000010000010101001101010011 P
b0 O
b10100101101001011010010110100101 N
b11111111111111111111111111111111 M
0L
b10100101101001011010010110100101 K
b10100101101001011010010110100101 J
b10100101101001011010010110100101 9
b11111111111111111111111111111111 8
b0 7
b0 6
b10100101101001011010010110100101 5
b11111111111111111111111111111111 4
b0 3
b10100101101001011010010110100101 "
0!
$end
#10000
b11110 "
b11110 J
b1010 5
b1010 9
b10100 4
b10100 8
b1 3
b1 7
b11110 K
b1010 N
b10100 M
b1 O
b10000010100010001000100 P
#20000
1!
b0 "
b0 J
b10100 5
b10100 9
b10 3
b10 7
1L
b0 K
b10100 N
b10 O
b10100110101010101000010 P
#30000
b1111000011110000111100001111 5
b1111000011110000111100001111 9
b11110000111100001111000011110000 4
b11110000111100001111000011110000 8
b11 3
b11 7
b1111000011110000111100001111 N
b11110000111100001111000011110000 M
b11 O
b10000010100111001000100 P
#40000
0!
b11111111111111111111111111111111 "
b11111111111111111111111111111111 J
b100 3
b100 7
0L
b11111111111111111111111111111111 K
b100 O
b100111101010010 P
#50000
b1011010010110100101101001011010 "
b1011010010110100101101001011010 J
b10100101101001011010010110100101 5
b10100101101001011010010110100101 9
b11111111111111111111111111111111 4
b11111111111111111111111111111111 8
b101 3
b101 7
b1011010010110100101101001011010 K
b10100101101001011010010110100101 N
b11111111111111111111111111111111 M
b101 O
b10110000100111101010010 P
#60000
b10000 "
b10000 J
b100 5
b100 9
b1 4
b1 8
b110 3
b110 7
b10000 K
b100 N
b1 M
b110 O
b10100110100110001001100 P
#70000
b1000000000000000000000000000 "
b1000000000000000000000000000 J
b10000000000000000000000000000000 4
b10000000000000000000000000000000 8
b111 3
b111 7
b1000000000000000000000000000 K
b10000000000000000000000000000000 M
b111 O
b10100110101001001001100 P
#80000
b11111000000000000000000000000000 "
b11111000000000000000000000000000 J
b1000 3
b1000 7
b11111000000000000000000000000000 K
b1000 O
b10100110101001001000001 P
#90000
b1 "
b1 J
b1 5
b1 9
b11111111111111111111111111111111 4
b11111111111111111111111111111111 8
b1001 3
b1001 7
b1 K
b1 N
b11111111111111111111111111111111 M
b1001 O
b10100110100110001010100 P
#100000
1!
b0 "
b0 J
b1010 3
b1010 7
1L
b0 K
b1010 O
b1010011010011000101010001010101 P
#110000
b10100 5
b10100 9
b1010 4
b1010 8
b1011 3
b1011 7
b10100 N
b1010 M
b1011 O
b10000100100111001000101 P
#120000
b1 5
b1 9
b11111111111111111111111111111111 4
b11111111111111111111111111111111 8
b1100 3
b1100 7
b1 N
b11111111111111111111111111111111 M
b1100 O
b10000100100110001010100 P
#130000
b1010 5
b1010 9
b10100 4
b10100 8
b1101 3
b1101 7
b1010 N
b10100 M
b1101 O
b10000100100011101000101 P
#140000
b101 4
b101 8
b1110 3
b1110 7
b101 M
b1110 O
b1000010010011000101010001010101 P
#150000
b11111111111111111111111111111111 4
b11111111111111111111111111111111 8
b1111 3
b1111 7
b11111111111111111111111111111111 M
b1111 O
b1000010010001110100010101010101 P
#160000
0!
b1010 4
b1010 8
b1011 3
b1011 7
0L
b1010 M
b1011 O
b1000010010011100100010101000110 P
