rtl/BITMANIP.v
module BITMANIP(
    input       [31:0]  SrcAE,
    input       [31:0]  SrcBE,
    input       [2:0]   BIT_Control,
    output reg  [31:0]  BIT_Result
);

integer i;

always @(*) begin
    case (BIT_Control)
        3'b000: begin              // clz (count leading zero)
            BIT_Result = 32'd32;     // Default if all zeros   
            for (i = 0; i < 32; i = i + 1) begin  // Loop from LSB to MSB
                if (SrcAE[i]) begin        
                    BIT_Result = 31 - i;
                end
            end
        end
        3'b001: begin              // cpop (population count)
            BIT_Result = 32'd0;    
            // Sums up all bits. Synthesizer turns this into parallel adder tree
            for (i = 0; i < 32; i = i + 1) begin
                BIT_Result = BIT_Result + SrcAE[i];
            end
        end 
        3'b010: begin              // rev8 (byte reverse)
            BIT_Result = {SrcAE[7:0], SrcAE[15:8], SrcAE[23:16], SrcAE[31:24]}; // using concatenation
        end
        3'b011: begin              // rol (rotate left)
            if (SrcBE[4:0] == 5'd0) begin  
                BIT_Result = SrcAE;
            end else begin
                BIT_Result = (SrcAE << SrcBE[4:0]) | (SrcAE >> (6'd32 - SrcBE[4:0]));
            end
        end
        3'b100: begin              // ror (Rotate Right)
            if (SrcBE[4:0] == 5'd0) begin  
                BIT_Result = SrcAE;
            end else begin
                BIT_Result = (SrcAE >> SrcBE[4:0]) | (SrcAE << (6'd32 - SrcBE[4:0]));
            end
        end
        default: BIT_Result = 32'h00000000;
    endcase  
end

endmodule

tb/tb_BITMANIP.v
`timescale 1ns/1ps

module tb_BITMANIP ();
    reg [31:0]  SrcAE;
    reg [31:0]  SrcBE;
    reg [2:0]   BIT_Control;
    wire [31:0] BIT_Result;

    integer error_count = 0;

    BITMANIP uut (
        .SrcAE(SrcAE),
        .SrcBE(SrcBE),
        .BIT_Control(BIT_Control),
        .BIT_Result(BIT_Result)
    );

    task test_bit;
        input [79:0] test_name;
        input [2:0] in_ctrl;
        input [31:0] in_a;
        input [31:0] in_b;
        input [31:0] exp_result;
        begin
            BIT_Control = in_ctrl;
            SrcAE       = in_a;
            SrcBE       = in_b;
            #10;
            if(BIT_Result == exp_result) begin
                $display("%-8s | [PASS]", test_name);
            end else begin
                $display("%-8s | [FAIL] Mismatch detected", test_name);
                error_count = error_count + 1;
            end

            $display("   Actual : BIT_Result = %h", BIT_Result);
            $display(" Expected : BIT_Result = %h", exp_result);
            $display("---------------------------------------");
        end
    endtask

    initial begin
        $dumpfile("build/bitmanip_waveform.vcd");
        $dumpvars(0, tb_BITMANIP);
        
        test_bit("clz",     3'b000, 32'h80000000, 32'd0, 32'h00000000);
        test_bit("clz",     3'b000, 32'h00000001, 32'd0, 32'h0000001F);
        test_bit("clz",     3'b000, 32'h80000000, 32'd0, 32'h00000000);
        test_bit("cpop",    3'b001, 32'h0000000F, 32'd0, 32'h00000004);
        test_bit("rev8",    3'b010, 32'h12345678, 32'd0, 32'h78563412);
        test_bit("rol",     3'b011, 32'h000000F0, 32'd4, 32'h00000F00);
        test_bit("ror",     3'b100, 32'h000000FF, 32'd4, 32'hF000000F);
        test_bit("default", 3'b111, 32'hFFFFFFFF, 32'd0, 32'h00000000);

        if (error_count == 0) begin
            $display(" 🎉 ALL BITMANIP TESTS PASSED! BITMANIP logic is fully verified.");
        end else begin
            $display(" ❌ SIMULATION FAILED: Total Mismatches Found = %0d", error_count);
        end
        
        $finish;
    end
endmodule

build/bitmanip_waveform.vcd
$date
	Wed Oct  7 06:30:12 2026
$end
$version
	Icarus Verilog
$end
$timescale
	1ps
$end
$scope module tb_BITMANIP $end
$var wire 32 ! BIT_Result [31:0] $end
$var reg 3 " BIT_Control [2:0] $end
$var reg 32 # SrcAE [31:0] $end
$var reg 32 $ SrcBE [31:0] $end
$var integer 32 % error_count [31:0] $end
$scope module uut $end
$var wire 3 & BIT_Control [2:0] $end
$var wire 32 ' SrcAE [31:0] $end
$var wire 32 ( SrcBE [31:0] $end
$var reg 32 ) BIT_Result [31:0] $end
$var integer 32 * i [31:0] $end
$upscope $end
$scope task test_bit $end
$var reg 32 + exp_result [31:0] $end
$var reg 32 , in_a [31:0] $end
$var reg 32 - in_b [31:0] $end
$var reg 3 . in_ctrl [2:0] $end
$var reg 80 / test_name [79:0] $end
$upscope $end
$upscope $end
$enddefinitions $end
$comment Show the parameter values. $end
$dumpall
$end
#0
$dumpvars
b11000110110110001111010 /
b0 .
b0 -
b10000000000000000000000000000000 ,
b0 +
b100000 *
b0 )
b0 (
b10000000000000000000000000000000 '
b0 &
b0 %
b0 $
b10000000000000000000000000000000 #
b0 "
b0 !
$end
#10000
b100000 *
b11111 !
b11111 )
b1 #
b1 '
b11111 +
b1 ,
#20000
b100000 *
b0 !
b0 )
b10000000000000000000000000000000 #
b10000000000000000000000000000000 '
b0 +
b10000000000000000000000000000000 ,
#30000
b100 !
b100 )
b100000 *
b1111 #
b1111 '
b1 "
b1 &
b100 +
b1111 ,
b1 .
b1100011011100000110111101110000 /
#40000
b1111000010101100011010000010010 !
b1111000010101100011010000010010 )
b10010001101000101011001111000 #
b10010001101000101011001111000 '
b10 "
b10 &
b1111000010101100011010000010010 +
b10010001101000101011001111000 ,
b10 .
b1110010011001010111011000111000 /
#50000
b111100000000 !
b111100000000 )
b100 $
b100 (
b11110000 #
b11110000 '
b11 "
b11 &
b111100000000 +
b100 -
b11110000 ,
b11 .
b11100100110111101101100 /
#60000
b11110000000000000000000000001111 !
b11110000000000000000000000001111 )
b11111111 #
b11111111 '
b100 "
b100 &
b11110000000000000000000000001111 +
b11111111 ,
b100 .
b11100100110111101110010 /
#70000
b0 !
b0 )
b0 $
b0 (
b11111111111111111111111111111111 #
b11111111111111111111111111111111 '
b111 "
b111 &
b0 +
b0 -
b11111111111111111111111111111111 ,
b111 .
b1100100011001010110011001100001011101010110110001110100 /
