rtl/Hazard_Unit.v
module Hazard_Unit (
    //Input for Data Forwarding (EX Stage)
    input       [4:0]   Rs1E,
    input       [4:0]   Rs2E,
    input       [4:0]   RdM, RdW,
    input               RegWriteM, RegWriteW,
    input               Mispredict_Flag,

    //Input for Load-Use Stalls (ID Stage)
    input       [4:0]   Rs1D,
    input       [4:0]   Rs2D,
    input       [4:0]   RdE,
    input       [1:0]   ResultSrcE, //bit 0 detect wheter EX stage is a Load instruction

    //Input for Control Hazards (EX Stage)
    input       [1:0]   PCSrcE,     //From Next PC Logic: >0 means Branch/Jump taken

    //Hazard Control Outputs
    output reg  [1:0]   ForwardAE, ForwardBE,
    output reg          StallF, StallD,
    output reg          FlushD, FlushE
);
    reg lwStall;

    always @(*) begin
        // Data Forwarding Logic 
            // add / lw / jal   instruction is legitimately writing a result back to register
            // Store and Branch instructions do not have a destination register

        //Forwarding for ALU Input A (Rs1E)
        if (RegWriteM && (RdM != 5'b0) && (RdM == Rs1E)) begin
            ForwardAE = 2'b10;      //forward from memory stage
        end else if (RegWriteW && (RdW != 5'b0) && (RdW == Rs1E)) begin
            ForwardAE = 2'b01;      //forward from writeback stage
        end else begin
            ForwardAE = 2'b00;
        end

        // Forwarding for ALU Input B (Rs2E)
        if (RegWriteM && (RdM != 5'b0) && (RdM == Rs2E)) begin
            ForwardBE = 2'b10;      // Forward from memory stage for operand B
        end else if (RegWriteW && (RdW != 5'b0) && (RdW == Rs2E)) begin
            ForwardBE = 2'b01;      // Forward from writeback stage for operand B
        end else begin
            ForwardBE = 2'b00;      // Default: use register file output for operand B
        end
    
        //Load-Use Stall Logic
            //Detect if the insturction in EX is a Load (ResultSrcE ==01) AND
            //its destination register matches either source register in ID.
            if ((ResultSrcE[0]==1'b1) && ((RdE==Rs1D)||(RdE==Rs2D))) begin
                lwStall = 1'b1;
            end else begin
                lwStall = 1'b0;
            end

        //Pipelined Stall and Flush routing (Control Hazard)
            //Flush --> create a NOP bubble --> all the data and control signals wiped out & forced to zero
            //1) Stall: Freeze PC (StallF) and ID stage (StallD) if Load-Use deteced
            StallF = lwStall;
            StallD = lwStall;

            //2) Flush ID: Clear instruction if Jump/Branch is taken
            // (PCSrcE = 01 for JAL/Branch, 10 for JALR)
            // (Mispredict_Flag for failed RAS guesses)
            if ((PCSrcE != 2'b00) ||(Mispredict_Flag == 1'b1)) begin
                FlushD = 1'b1;
            end else begin
                FlushD = 1'b0;
            end

            //3) Flush EX: Insert a bubble if Load-Use stalled OR if Jump/Branch taken OR Misprediction
            if ((lwStall) || (PCSrcE != 2'b00) ||(Mispredict_Flag == 1'b1)) begin
                FlushE = 1'b1;
            end else begin
                FlushE = 1'b0;
            end
    end
endmodule

tb/tb_Hazard_Unit.v
`timescale 1ns / 1ps

module tb_Hazard_Unit();

    // 1. Declare inputs as regs
    reg [4:0] rs1e, rs2e;
    reg [4:0] rdm, rdw;
    reg       regwritem, regwritew;
    reg [4:0] rs1d, rs2d;
    reg [4:0] rde;
    reg [1:0] resultsrce;
    reg [1:0] pcscrce;
    reg       mispredict_flag; 

    // 2. Declare outputs as wires
    wire [1:0] forwardae, forwardbe;
    wire       stallf, stalld;
    wire       flushd, flushe;

    // Error tracking counter
    integer error_count = 0;

    // 3. Instantiate the Device Under Test (DUT)
    Hazard_Unit dut (
        .Rs1E(rs1e),
        .Rs2E(rs2e),
        .RdM(rdm),
        .RdW(rdw),
        .RegWriteM(regwritem),
        .RegWriteW(regwritew),
        .Mispredict_Flag(mispredict_flag), // FIXED: Removed trailing comma and mapped to reg
        .Rs1D(rs1d),
        .Rs2D(rs2d),
        .RdE(rde),
        .ResultSrcE(resultsrce),
        .PCSrcE(pcscrce),
        .ForwardAE(forwardae),
        .ForwardBE(forwardbe),
        .StallF(stallf),
        .StallD(stalld),
        .FlushD(flushd),
        .FlushE(flushe)
    );

    // 4. Automated Testing Task with Expected Values
    task test_hazard;
        input [127:0] test_name;
        // Inputs
        input [4:0] in_rs1e, in_rs2e;
        input [4:0] in_rdm, in_rdw;
        input       in_regwritem, in_regwritew;
        input       in_mispredict;
        input [4:0] in_rs1d, in_rs2d;
        input [4:0] in_rde;
        input [1:0] in_resultsrce;
        input [1:0] in_pcscrce;
        // Expected outputs
        input [1:0] exp_forwardae, exp_forwardbe;
        input       exp_stallf, exp_stalld;
        input       exp_flushd, exp_flushe;
        begin
            // Apply inputs
            rs1e            = in_rs1e;
            rs2e            = in_rs2e;
            rdm             = in_rdm;
            rdw             = in_rdw;
            regwritem       = in_regwritem;
            regwritew       = in_regwritew;
            mispredict_flag = in_mispredict; // FIXED: Mapped to declared register
            rs1d            = in_rs1d;
            rs2d            = in_rs2d;
            rde             = in_rde;
            resultsrce      = in_resultsrce;
            pcscrce         = in_pcscrce;
            
            #10; // Wait for combinational logic to settle

            // Compare actual vs expected outputs
            if (forwardae  === exp_forwardae  &&
                forwardbe  === exp_forwardbe  &&
                stallf     === exp_stallf     &&
                stalld     === exp_stalld     &&
                flushd     === exp_flushd     &&
                flushe     === exp_flushe) begin
                
                $display("%-25s | [PASS]", test_name);
            end else begin
                $display("%-25s | [FAIL] ❌ MISMATCH DETECTED!", test_name);
                error_count = error_count + 1;
            end

            // Display Actual vs Expected rows
            $display("    Actual   : FwdAE=%b FwdBE=%b StallF=%b StallD=%b FlushD=%b FlushE=%b", 
                     forwardae, forwardbe, stallf, stalld, flushd, flushe);
            $display("    Expected : FwdAE=%b FwdBE=%b StallF=%b StallD=%b FlushD=%b FlushE=%b", 
                     exp_forwardae, exp_forwardbe, exp_stallf, exp_stalld, exp_flushd, exp_flushe);
            $display("--------------------------------------------------------------------------------------------------------");
        end
    endtask

    // 5. Run the Test Sequence
    initial begin
        $dumpfile("build/hazard_waveform.vcd");
        $dumpvars(0,tb_Hazard_Unit);
        $display("========================================================================================================");
        $display("                        AUTOMATED HAZARD UNIT VERIFICATION SUITE                                ");
        $display("========================================================================================================");

        // --- SECTION 1: Default / No Hazards ---
        // FIXED: Added 1'b0 for in_mispredict in all legacy tests to fix argument shifting
        test_hazard("NO_HAZARD", 
                    5'd1, 5'd2, 5'd0, 5'd0, 1'b0, 1'b0, 1'b0, // <--- in_mispredict = 0
                    5'd3, 5'd4, 5'd0, 2'b00, 2'b00, 
                    2'b00, 2'b00, 1'b0, 1'b0, 1'b0, 1'b0);

        // --- SECTION 2: Data Forwarding A & B Tests ---
        test_hazard("FWD_A_MEM", 
                    5'd5, 5'd2, 5'd5, 5'd0, 1'b1, 1'b0, 1'b0, 
                    5'd0, 5'd0, 5'd0, 2'b00, 2'b00, 
                    2'b10, 2'b00, 1'b0, 1'b0, 1'b0, 1'b0);

        test_hazard("FWD_A_WB", 
                    5'd7, 5'd2, 5'd0, 5'd7, 1'b0, 1'b1, 1'b0, 
                    5'd0, 5'd0, 5'd0, 2'b00, 2'b00, 
                    2'b01, 2'b00, 1'b0, 1'b0, 1'b0, 1'b0);

        test_hazard("FWD_B_MEM", 
                    5'd1, 5'd8, 5'd8, 5'd0, 1'b1, 1'b0, 1'b0, 
                    5'd0, 5'd0, 5'd0, 2'b00, 2'b00, 
                    2'b00, 2'b10, 1'b0, 1'b0, 1'b0, 1'b0);

        test_hazard("FWD_MEM_PRIORITY", 
                    5'd9, 5'd2, 5'd9, 5'd9, 1'b1, 1'b1, 1'b0, 
                    5'd0, 5'd0, 5'd0, 2'b00, 2'b00, 
                    2'b10, 2'b00, 1'b0, 1'b0, 1'b0, 1'b0);

        test_hazard("IGNORE_X0_FWD", 
                    5'd0, 5'd2, 5'd0, 5'd0, 1'b1, 1'b1, 1'b0, 
                    5'd0, 5'd0, 5'd0, 2'b00, 2'b00, 
                    2'b00, 2'b00, 1'b0, 1'b0, 1'b0, 1'b0);

        // --- SECTION 3: Load-Use Stall Tests ---
        test_hazard("LOAD_USE_STALL_Rs1", 
                    5'd0, 5'd0, 5'd0, 5'd0, 1'b0, 1'b0, 1'b0, 
                    5'd5, 5'd2, 5'd5, 2'b01, 2'b00, 
                    2'b00, 2'b00, 1'b1, 1'b1, 1'b0, 1'b1);

        test_hazard("LOAD_USE_STALL_Rs2", 
                    5'd0, 5'd0, 5'd0, 5'd0, 1'b0, 1'b0, 1'b0, 
                    5'd2, 5'd6, 5'd6, 2'b01, 2'b00, 
                    2'b00, 2'b00, 1'b1, 1'b1, 1'b0, 1'b1);

        test_hazard("NO_STALL_ALU_MATCH", 
                    5'd0, 5'd0, 5'd0, 5'd0, 1'b0, 1'b0, 1'b0, 
                    5'd5, 5'd2, 5'd5, 2'b00, 2'b00, 
                    2'b00, 2'b00, 1'b0, 1'b0, 1'b0, 1'b0);

        // --- SECTION 4: Control Hazard (Branch / Jump Taken) Tests ---
        test_hazard("BRANCH_TAKEN_FLUSH", 
                    5'd0, 5'd0, 5'd0, 5'd0, 1'b0, 1'b0, 1'b0, 
                    5'd0, 5'd0, 5'd0, 2'b00, 2'b01, 
                    2'b00, 2'b00, 1'b0, 1'b0, 1'b1, 1'b1);

        // --- SECTION 5: RAS Misprediction Tests (NEW) ---
        // Test: Branch Monitor detects RAS misprediction. Expected: Flush both stages.
        test_hazard("RAS_MISPREDICT_FLUSH", 
                    5'd0, 5'd0, 5'd0, 5'd0, 1'b0, 1'b0, 1'b1, // <--- in_mispredict = 1
                    5'd0, 5'd0, 5'd0, 2'b00, 2'b00,           // Normal execution otherwise
                    2'b00, 2'b00, 1'b0, 1'b0, 1'b1, 1'b1);    // EXPECT: FlushD = 1, FlushE = 1

        // Test: Load-Use Stall happens simultaneously with a RAS misprediction.
        // Expected: Control flush should override stalls (Stall=1, FlushD=1, FlushE=1).
        test_hazard("RAS_MISPREDICT_WITH_STALL", 
                    5'd0, 5'd0, 5'd0, 5'd0, 1'b0, 1'b0, 1'b1, // <--- in_mispredict = 1
                    5'd5, 5'd2, 5'd5, 2'b01, 2'b00,           // Load-Use condition triggered
                    2'b00, 2'b00, 1'b1, 1'b1, 1'b1, 1'b1);    // EXPECT: Stall and Flushes go high


        // --- Final Summary Report ---
        $display("========================================================================================================");
        if (error_count == 0) begin
            $display(" 🎉 ALL HAZARD UNIT TESTS PASSED! Forwarding, Stalls, and Flushes are fully verified.");
        end else begin
            $display(" ❌ SIMULATION FAILED: Total Mismatches Found = %0d", error_count);
        end
        $display("========================================================================================================");
        $finish;
    end

endmodule

build/hazard_waveform.vcd
$date
	Thu Oct  8 10:38:24 2026
$end
$version
	Icarus Verilog
$end
$timescale
	1ps
$end
$scope module tb_Hazard_Unit $end
$var wire 1 ! stallf $end
$var wire 1 " stalld $end
$var wire 2 # forwardbe [1:0] $end
$var wire 2 $ forwardae [1:0] $end
$var wire 1 % flushe $end
$var wire 1 & flushd $end
$var reg 1 ' mispredict_flag $end
$var reg 2 ( pcscrce [1:0] $end
$var reg 5 ) rde [4:0] $end
$var reg 5 * rdm [4:0] $end
$var reg 5 + rdw [4:0] $end
$var reg 1 , regwritem $end
$var reg 1 - regwritew $end
$var reg 2 . resultsrce [1:0] $end
$var reg 5 / rs1d [4:0] $end
$var reg 5 0 rs1e [4:0] $end
$var reg 5 1 rs2d [4:0] $end
$var reg 5 2 rs2e [4:0] $end
$var integer 32 3 error_count [31:0] $end
$scope module dut $end
$var wire 1 ' Mispredict_Flag $end
$var wire 2 4 PCSrcE [1:0] $end
$var wire 5 5 RdE [4:0] $end
$var wire 5 6 RdM [4:0] $end
$var wire 5 7 RdW [4:0] $end
$var wire 1 , RegWriteM $end
$var wire 1 - RegWriteW $end
$var wire 2 8 ResultSrcE [1:0] $end
$var wire 5 9 Rs1D [4:0] $end
$var wire 5 : Rs1E [4:0] $end
$var wire 5 ; Rs2D [4:0] $end
$var wire 5 < Rs2E [4:0] $end
$var reg 1 & FlushD $end
$var reg 1 % FlushE $end
$var reg 2 = ForwardAE [1:0] $end
$var reg 2 > ForwardBE [1:0] $end
$var reg 1 " StallD $end
$var reg 1 ! StallF $end
$var reg 1 ? lwStall $end
$upscope $end
$scope task test_hazard $end
$var reg 1 @ exp_flushd $end
$var reg 1 A exp_flushe $end
$var reg 2 B exp_forwardae [1:0] $end
$var reg 2 C exp_forwardbe [1:0] $end
$var reg 1 D exp_stalld $end
$var reg 1 E exp_stallf $end
$var reg 1 F in_mispredict $end
$var reg 2 G in_pcscrce [1:0] $end
$var reg 5 H in_rde [4:0] $end
$var reg 5 I in_rdm [4:0] $end
$var reg 5 J in_rdw [4:0] $end
$var reg 1 K in_regwritem $end
$var reg 1 L in_regwritew $end
$var reg 2 M in_resultsrce [1:0] $end
$var reg 5 N in_rs1d [4:0] $end
$var reg 5 O in_rs1e [4:0] $end
$var reg 5 P in_rs2d [4:0] $end
$var reg 5 Q in_rs2e [4:0] $end
$var reg 128 R test_name [127:0] $end
$upscope $end
$upscope $end
$enddefinitions $end
$comment Show the parameter values. $end
$dumpall
$end
#0
$dumpvars
b10011100100111101011111010010000100000101011010010000010101001001000100 R
b10 Q
b100 P
b1 O
b11 N
b0 M
0L
0K
b0 J
b0 I
b0 H
b0 G
0F
0E
0D
b0 C
b0 B
0A
0@
0?
b0 >
b0 =
b10 <
b100 ;
b1 :
b11 9
b0 8
b0 7
b0 6
b0 5
b0 4
b0 3
b10 2
b100 1
b1 0
b11 /
b0 .
0-
0,
b0 +
b0 *
b0 )
b0 (
0'
0&
0%
b0 $
b0 #
0"
0!
$end
#10000
b10 $
b10 =
b0 1
b0 ;
b0 /
b0 9
1,
b101 *
b101 6
b101 0
b101 :
b10 B
b0 P
b0 N
1K
b101 I
b101 O
b10001100101011101000100010111110100000101011111010011010100010101001101 R
#20000
b1 $
b1 =
1-
0,
b111 +
b111 7
b0 *
b0 6
b111 0
b111 :
b1 B
1L
0K
b111 J
b0 I
b111 O
b100011001010111010001000101111101000001010111110101011101000010 R
#30000
b10 #
b10 >
b0 $
b0 =
0-
1,
b0 +
b0 7
b1000 *
b1000 6
b1000 2
b1000 <
b1 0
b1 :
b10 C
b0 B
0L
1K
b0 J
b1000 I
b1000 Q
b1 O
b10001100101011101000100010111110100001001011111010011010100010101001101 R
#40000
b0 #
b0 >
b10 $
b10 =
1-
b1001 +
b1001 7
b1001 *
b1001 6
b10 2
b10 <
b1001 0
b1001 :
b0 C
b10 B
1L
b1001 J
b1001 I
b10 Q
b1001 O
b1000110010101110100010001011111010011010100010101001101010111110101000001010010010010010100111101010010010010010101010001011001 R
#50000
b0 $
b0 =
b0 +
b0 7
b0 *
b0 6
b0 0
b0 :
b0 B
b0 J
b0 I
b0 O
b1001001010001110100111001001111010100100100010101011111010110000011000001011111010001100101011101000100 R
#60000
1%
1"
1!
1?
b1 .
b1 8
b101 )
b101 5
b10 1
b10 ;
b101 /
b101 9
0-
0,
b0 2
b0 <
1A
1D
1E
b1 M
b101 H
b10 P
b101 N
0L
0K
b0 Q
b1000001010001000101111101010101010100110100010101011111010100110101010001000001010011000100110001011111010100100111001100110001 R
#70000
b110 )
b110 5
b110 1
b110 ;
b10 /
b10 9
b110 H
b110 P
b10 N
b1000001010001000101111101010101010100110100010101011111010100110101010001000001010011000100110001011111010100100111001100110010 R
#80000
0%
0"
0!
0?
b0 .
b0 8
b101 )
b101 5
b10 1
b10 ;
b101 /
b101 9
0A
0D
0E
b0 M
b101 H
b10 P
b101 N
b1011111010100110101010001000001010011000100110001011111010000010100110001010101010111110100110101000001010101000100001101001000 R
#90000
1%
1&
b1 (
b1 4
b0 )
b0 5
b0 1
b0 ;
b0 /
b0 9
1A
1@
b1 G
b0 H
b0 P
b0 N
b1000001010011100100001101001000010111110101010001000001010010110100010101001110010111110100011001001100010101010101001101001000 R
#100000
b0 (
b0 4
1'
b0 G
1F
b1001101010010010101001101010000010100100100010101000100010010010100001101010100010111110100011001001100010101010101001101001000 R
#110000
1"
1!
1?
b1 .
b1 8
b101 )
b101 5
b10 1
b10 ;
b101 /
b101 9
1D
1E
b1 M
b101 H
b10 P
b101 N
b1000101010001000100100101000011010101000101111101010111010010010101010001001000010111110101001101010100010000010100110001001100 R
