rtl/LSU.v
module LSU (
    input       [2:0]   funct3M,
    input       [1:0]   ALUResultM,         //bottom 2 bits for alignment
    input       [31:0]  RD,                 //RD from DMEM, then to ReadDataW
    output reg  [3:0]   BW,                 //BW from funct3M, thento DMEM
    output reg  [31:0]  Formatted_ReadDataM 
);

always @(*) begin
    //Default
    BW = 4'b0000;
    Formatted_ReadDataM = 32'h00000000;

    //Write path -- generate byte enable (BW) for DMEM
    //bottom 2 bit of funct3M: 00(sb), 01(sh), 10(sw)
    /*NOTE: Load instruction share these code, 
    but DMEM will just ignore the BW output if WE pin is set to 0 */
    case (funct3M[1:0])
        2'b00: begin
            case (ALUResultM)       //sb, save byte
                2'b00: BW = 4'b0001;
                2'b01: BW = 4'b0010;
                2'b10: BW = 4'b0100;
                2'b11: BW = 4'b1000;
            endcase
        end
        2'b01: begin
            case (ALUResultM[1])    //sh, save halfword
                1'b0: BW = 4'b0011;
                1'b1: BW = 4'b1100;
            endcase
        end
        2'b10: begin
            BW = 4'b1111;           //sw, save word
        end
    endcase

    //Read path
    case (funct3M)
        3'b000: begin   //lb (load byte, sign-extended)
            case (ALUResultM)
                2'b00: Formatted_ReadDataM = {{24{RD[7]}}, RD[7:0]};
                2'b01: Formatted_ReadDataM = {{24{RD[15]}}, RD[15:8]};
                2'b10: Formatted_ReadDataM = {{24{RD[23]}}, RD[23:16]};
                2'b11: Formatted_ReadDataM = {{24{RD[23]}}, RD[23:16]};
            endcase
        end
        3'b100: begin   //lbu (load byte unsigned, zero-extended)
            case (ALUResultM)
                2'b00: Formatted_ReadDataM = {24'b0, RD[7:0]};
                2'b01: Formatted_ReadDataM = {24'b0, RD[15:8]};
                2'b10: Formatted_ReadDataM = {24'b0, RD[23:16]};
                2'b11: Formatted_ReadDataM = {24'b0, RD[23:16]};
            endcase
        end
        3'b001: begin   //lh (load halfword, sign-extended)
            case (ALUResultM[1])
                1'b0: Formatted_ReadDataM = {{16{RD[15]}}, RD[15:0]};
                1'b1: Formatted_ReadDataM = {{16{RD[31]}}, RD[31:16]};
            endcase
        end
        3'b101: begin   //lhu (Load Halfword Unsigned, Zero-Extended)
            case (ALUResultM[1])
                1'b0: Formatted_ReadDataM = {16'b0, RD[15:0]};
                1'b1: Formatted_ReadDataM = {16'b0, RD[31:16]};
            endcase
        end
        3'b010: begin   //lw (load word)
            Formatted_ReadDataM = RD;
        end
        default: begin
            Formatted_ReadDataM = RD;
        end
    endcase
end
endmodule

tb/tb_LSU.v
`timescale 1ns / 1ps

module tb_LSU_all();

    // Inputs to LSU
    reg  [2:0]  funct3M;
    reg  [1:0]  ALUResultM;
    reg  [31:0] RD;
    
    // Outputs from LSU
    wire [3:0]  BW;
    wire [31:0] Formatted_ReadDataM;

    // Error tracking counter
    integer error_count = 0;

    // Instantiate the Unit Under Test (UUT)
    LSU uut (
        .funct3M(funct3M),
        .ALUResultM(ALUResultM),
        .RD(RD),
        .BW(BW),
        .Formatted_ReadDataM(Formatted_ReadDataM)
    );

    // Automated Testing Task with Side-by-Side Expected vs Actual Display
    task test_lsu;
        input [79:0] inst_name;
        input [2:0]  in_f3;
        input [1:0]  in_alu;
        input [31:0] in_rd;
        input [3:0]  exp_bw;
        input [31:0] exp_data;
        begin
            funct3M    = in_f3;
            ALUResultM = in_alu;
            RD         = in_rd;
            #10; // Wait for combinational logic to settle

            if (BW === exp_bw && Formatted_ReadDataM === exp_data) begin
                $display("%-5s | [PASS] | BW [Exp:%b | Act:%b] | Data [Exp:%h | Act:%h]", 
                         inst_name, exp_bw, BW, exp_data, Formatted_ReadDataM);
            end else begin
                $display("%-5s | [FAIL] | BW [Exp:%b | Act:%b] | Data [Exp:%h | Act:%h] ❌", 
                         inst_name, exp_bw, BW, exp_data, Formatted_ReadDataM);
                error_count = error_count + 1;
            end
        end
    endtask

    initial begin
        $dumpfile("build/lsu_all_waveform.vcd");
        $dumpvars(0, tb_LSU_all);

        $display("========================================================================================================");
        $display("                               AUTOMATED LSU VERIFICATION SUITE (WITH EXPECTED VALUES)                  ");
        $display("========================================================================================================");

        // ================================================================================================================
        // format: test_lsu("NAME", funct3, ALUResult[1:0], RD_input, expected_BW, expected_Formatted_Data)
        // ================================================================================================================

        // -----------------------------------------
        // PART 1: STORE INSTRUCTIONS
        // -----------------------------------------
        test_lsu("SB",   3'b000, 2'b10, 32'h00000000, 4'b0100, 32'h00000000);
        test_lsu("SH",   3'b001, 2'b10, 32'h00000000, 4'b1100, 32'h00000000);
        test_lsu("SW",   3'b010, 2'b00, 32'h00000000, 4'b1111, 32'h00000000);

        // -----------------------------------------
        // PART 2: LOAD INSTRUCTIONS
        // -----------------------------------------
        test_lsu("LB",   3'b000, 2'b00, 32'h0000008A, 4'b0001, 32'hFFFFFF8A);
        test_lsu("LBU",  3'b100, 2'b00, 32'h0000008A, 4'b0001, 32'h0000008A);
        test_lsu("LH",   3'b001, 2'b00, 32'h00008FFF, 4'b0011, 32'hFFFF8FFF);
        test_lsu("LHU",  3'b101, 2'b00, 32'h00008FFF, 4'b0011, 32'h00008FFF);
        test_lsu("LW",   3'b010, 2'b00, 32'hDEADBEEF, 4'b1111, 32'hDEADBEEF);

        // Final Summary Report
        $display("========================================================================================================");
        if (error_count == 0) begin
            $display(" 🎉 ALL LSU TESTS PASSED! Load-Store Unit logic is fully verified.");
        end else begin
            $display(" ❌ SIMULATION FAILED: Total Mismatches Found = %0d", error_count);
        end
        $display("========================================================================================================");
        $finish;
    end

endmodule

build/lsu_all_waveform.vcd
$date
	Mon Oct  5 09:28:06 2026
$end
$version
	Icarus Verilog
$end
$timescale
	1ps
$end
$scope module tb_LSU_all $end
$var wire 32 ! Formatted_ReadDataM [31:0] $end
$var wire 4 " BW [3:0] $end
$var reg 2 # ALUResultM [1:0] $end
$var reg 32 $ RD [31:0] $end
$var reg 3 % funct3M [2:0] $end
$var integer 32 & error_count [31:0] $end
$scope module uut $end
$var wire 2 ' ALUResultM [1:0] $end
$var wire 32 ( RD [31:0] $end
$var wire 3 ) funct3M [2:0] $end
$var reg 4 * BW [3:0] $end
$var reg 32 + Formatted_ReadDataM [31:0] $end
$upscope $end
$scope task test_lsu $end
$var reg 4 , exp_bw [3:0] $end
$var reg 32 - exp_data [31:0] $end
$var reg 2 . in_alu [1:0] $end
$var reg 3 / in_f3 [2:0] $end
$var reg 32 0 in_rd [31:0] $end
$var reg 80 1 inst_name [79:0] $end
$upscope $end
$upscope $end
$enddefinitions $end
$comment Show the parameter values. $end
$dumpall
$end
#0
$dumpvars
b101001101000010 1
b0 0
b0 /
b10 .
b0 -
b100 ,
b0 +
b100 *
b0 )
b0 (
b10 '
b0 &
b0 %
b0 $
b10 #
b100 "
b0 !
$end
#10000
b1100 "
b1100 *
b1 %
b1 )
b1100 ,
b1 /
b101001101001000 1
#20000
b1111 "
b1111 *
b0 #
b0 '
b10 %
b10 )
b1111 ,
b0 .
b10 /
b101001101010111 1
#30000
b11111111111111111111111110001010 !
b11111111111111111111111110001010 +
b1 "
b1 *
b10001010 $
b10001010 (
b0 %
b0 )
b11111111111111111111111110001010 -
b1 ,
b10001010 0
b0 /
b100110001000010 1
#40000
b10001010 !
b10001010 +
b1 "
b1 *
b100 %
b100 )
b10001010 -
b100 /
b10011000100001001010101 1
#50000
b11111111111111111000111111111111 !
b11111111111111111000111111111111 +
b11 "
b11 *
b1000111111111111 $
b1000111111111111 (
b1 %
b1 )
b11111111111111111000111111111111 -
b11 ,
b1000111111111111 0
b1 /
b100110001001000 1
#60000
b1000111111111111 !
b1000111111111111 +
b11 "
b11 *
b101 %
b101 )
b1000111111111111 -
b101 /
b10011000100100001010101 1
#70000
b11011110101011011011111011101111 !
b11011110101011011011111011101111 +
b1111 "
b1111 *
b11011110101011011011111011101111 $
b11011110101011011011111011101111 (
b10 %
b10 )
b11011110101011011011111011101111 -
b1111 ,
b11011110101011011011111011101111 0
b10 /
b100110001010111 1
