rtl/Register_File.v
    //output @ output wire  -- continuous assignment (assign)
    //output reg            -- procedural block (always@(*))

module Register_File # (
    parameter p_DATA_DMEM_SIZE = 2**12  //2**10 -- 1kb @ 2**12 -- 4kb
)(
    input wire  [4:0]   A1,         //Rs1D, source register 1 address
    input wire  [4:0]   A2,         //Rs2D, source register 2 address
    input wire  [4:0]   A3,         //RdW, destination register address
    input wire  [31:0]  ResultW,    //data write back
    input wire          RegWriteW,  //write enable signal
    input wire          i_Clk,
    input wire          i_Rst,
    output      [31:0]  RD1D,       //read data 1
    output      [31:0]  RD2D        //read data 2
);

    //Constants for Bare-Metal Initialization
    localparam c_SP_Index = 2;
    localparam c_GP_Index = 3;
    localparam c_GP_Initial_Value = 32'h10010000;
    localparam c_SP_Initial_Value = c_GP_Initial_Value + p_DATA_DMEM_SIZE - 4;

    //Register Data Array
    reg [31:0] r_Registers [0:31];

    integer i;

    /*Sequential Write Logic (-ev Edge Triggered)*/
    always @(negedge i_Clk or posedge i_Rst) begin
        if(i_Rst) begin
            //Initialize registers on reset
            for (i=0;i<32;i=i+1) begin
                case (i)
                    c_SP_Index: r_Registers[i] <= c_SP_Initial_Value;
                    c_GP_Index: r_Registers[i] <= c_GP_Initial_Value;
                    default:    r_Registers[i] <= 32'h0;
                endcase
            end
        end else begin
            //Write new data if enabled, protecting register x0
            if (RegWriteW && A3 != 5'h0) begin
                r_Registers[A3] <= ResultW;
            end
        end
    end

    /*Combinational Read Logic (Asynchronous)*/
    //using ternary operator ensure x0 ALWAYS read as 0, even if a bug bypassed the write protection
    assign RD1D = (A1==5'h0) ? 32'h0 : r_Registers[A1];
    assign RD2D = (A2==5'h0) ? 32'h0 : r_Registers[A2];
endmodule

tb/tb_Register_File.v
`timescale 1ns / 1ps

module tb_Register_File();

    // 1. Declare Testbench Signals
    reg  [4:0]  A1;
    reg  [4:0]  A2;
    reg  [4:0]  A3;
    reg  [31:0] ResultW;
    reg         RegWriteW;
    reg         i_Clk;
    reg         i_Rst;

    wire [31:0] RD1D;
    wire [31:0] RD2D;

    // 2. Instantiate the Register File
    Register_File #(
        .p_DATA_DMEM_SIZE(4096)
    ) uut (
        .A1(A1),
        .A2(A2),
        .A3(A3),
        .ResultW(ResultW),
        .RegWriteW(RegWriteW),
        .i_Clk(i_Clk),
        .i_Rst(i_Rst),
        .RD1D(RD1D),
        .RD2D(RD2D)
    );

    // 3. Generate a 100MHz Clock (Toggles every 5ns)
    always #5 i_Clk = ~i_Clk;

    // 4. Test Sequence
    initial begin
        // Output waveform to the build folder we just discussed!
        $dumpfile("build/rf_waveform.vcd");
        $dumpvars(0, tb_Register_File);

        $display("=== STARTING REGISTER FILE TEST ===");

        // Initialize all inputs
        i_Clk = 0;
        i_Rst = 1; // Assert reset
        A1 = 0; A2 = 0; A3 = 0;
        ResultW = 0; RegWriteW = 0;

        // ---------------------------------------------------------
        // TEST 1: Reset & Bare-Metal Initialization
        // ---------------------------------------------------------
        #15;        // Hold reset for a few clock cycles
        i_Rst = 0;  // Release reset
        #10;        
        A1 = 5'd2;  // Read sp (x2)
        A2 = 5'd3;  // Read gp (x3)
        #1;         // Wait 1ns for combinational read
        // Expected SP: 0x10010000 + 4096 - 4 = 0x10010FFC
        $display("1. Reset Check -> Expected SP: 10010ffc, GP: 10010000 | Actual SP: %h, GP: %h", RD1D, RD2D);

        // ---------------------------------------------------------
        // TEST 2: Normal Write & Read
        // ---------------------------------------------------------
        // We set up the data on the posedge, so it is cleanly captured on the negedge
        @(posedge i_Clk); 
        A3 = 5'd5;              // Target register x5
        ResultW = 32'hDEADBEEF; // Data to write
        RegWriteW = 1;          // Enable write
        
        @(posedge i_Clk);       // Wait for the next clock cycle (write happened on the negedge between these)
        RegWriteW = 0;          // Turn off write
        A1 = 5'd5;              // Read x5
        #1;
        $display("2. Normal Write (x5) -> Expected: deadbeef | Actual: %h", RD1D);

        // ---------------------------------------------------------
        // TEST 3: x0 Hardwired Protection
        // ---------------------------------------------------------
        @(posedge i_Clk);
        A3 = 5'd0;              // Target register x0
        ResultW = 32'hFFFFFFFF; // Try to overwrite it with 1s
        RegWriteW = 1;
        
        @(posedge i_Clk);
        RegWriteW = 0;
        A1 = 5'd0;              // Read x0
        #1;
        $display("3. x0 Protection -> Expected: 00000000 | Actual: %h", RD1D);

        // ---------------------------------------------------------
        // TEST 4: RegWrite Enable Signal Check
        // ---------------------------------------------------------
        @(posedge i_Clk);
        A3 = 5'd10;             // Target register x10
        ResultW = 32'h12345678; 
        RegWriteW = 0;          // WRITE DISABLED!
        
        @(posedge i_Clk);
        A1 = 5'd10;             // Read x10
        #1;
        $display("4. RegWrite Disabled -> Expected: 00000000 | Actual: %h", RD1D);

        $display("=== TESTS COMPLETED ===");
        $finish;
    end

endmodule

build/rf_waveform.vcd
$date
	Sat Sep 26 16:46:19 2026
$end
$version
	Icarus Verilog
$end
$timescale
	1ps
$end
$scope module tb_Register_File $end
$var wire 32 ! RD2D [31:0] $end
$var wire 32 " RD1D [31:0] $end
$var reg 5 # A1 [4:0] $end
$var reg 5 $ A2 [4:0] $end
$var reg 5 % A3 [4:0] $end
$var reg 1 & RegWriteW $end
$var reg 32 ' ResultW [31:0] $end
$var reg 1 ( i_Clk $end
$var reg 1 ) i_Rst $end
$scope module uut $end
$var wire 5 * A1 [4:0] $end
$var wire 5 + A2 [4:0] $end
$var wire 5 , A3 [4:0] $end
$var wire 1 & RegWriteW $end
$var wire 32 - ResultW [31:0] $end
$var wire 1 ( i_Clk $end
$var wire 1 ) i_Rst $end
$var wire 32 . RD2D [31:0] $end
$var wire 32 / RD1D [31:0] $end
$var parameter 32 0 c_GP_Index $end
$var parameter 32 1 c_GP_Initial_Value $end
$var parameter 32 2 c_SP_Index $end
$var parameter 34 3 c_SP_Initial_Value $end
$var parameter 32 4 p_DATA_DMEM_SIZE $end
$var integer 32 5 i [31:0] $end
$upscope $end
$upscope $end
$enddefinitions $end
$comment Show the parameter values. $end
$dumpall
b1000000000000 4
b10000000000010000111111111100 3
b10 2
b10000000000010000000000000000 1
b11 0
$end
#0
$dumpvars
b100000 5
b0 /
b0 .
b0 -
b0 ,
b0 +
b0 *
1)
0(
b0 '
0&
b0 %
b0 $
b0 #
b0 "
b0 !
$end
#5000
1(
#10000
b100000 5
0(
#15000
1(
0)
#20000
0(
#25000
b10000000000010000000000000000 !
b10000000000010000000000000000 .
b10000000000010000111111111100 "
b10000000000010000111111111100 /
1(
b11 $
b11 +
b10 #
b10 *
#30000
0(
#35000
1&
b11011110101011011011111011101111 '
b11011110101011011011111011101111 -
b101 %
b101 ,
1(
#40000
0(
#45000
b11011110101011011011111011101111 "
b11011110101011011011111011101111 /
b101 #
b101 *
0&
1(
#50000
0(
#55000
1&
b11111111111111111111111111111111 '
b11111111111111111111111111111111 -
b0 %
b0 ,
1(
#60000
0(
#65000
b0 "
b0 /
b0 #
b0 *
0&
1(
#70000
0(
#75000
b10010001101000101011001111000 '
b10010001101000101011001111000 -
b1010 %
b1010 ,
1(
#80000
0(
#85000
b1010 #
b1010 *
1(
